{
    "freq_is": {
        "a repeating pattern of light and dark bands": 1,
        "the bands are of different widths": 1,
        "the bands may be of different colors": 1,
        "the bands may be curved or straight": 1,
        "the bands may be parallel or intersecting": 1,
        "an uneven or mottled surface": 1,
        "a variety of colors or shades": 1,
        "a raised or bumpy texture": 1,
        "a matte finish": 1,
        "three or more strands of material woven together": 1,
        "a tight, interlocking pattern": 2,
        "small, round, and raised bumps": 1,
        "a smooth or glossy surface": 2,
        "a three-dimensional appearance": 4,
        "a light-reflecting quality": 1,
        "an uneven surface": 1,
        "raised or indented areas": 1,
        "a rough or bumpy feel": 1,
        "a repeating pattern of squares or rectangles": 2,
        "alternating light and dark colors": 1,
        "sharp, defined lines between the squares or rectangles": 1,
        "a web-like pattern": 1,
        "made of thin, silky strands": 1,
        "often found in dark, damp places": 1,
        "can be sticky to the touch": 1,
        "can be difficult to remove once entangled": 1,
        "a surface with cracks": 1,
        "the cracks may be straight or curved": 1,
        "the cracks may be of different sizes": 1,
        "the cracks may be close together or far apart": 1,
        "the cracks may be deep or shallow": 1,
        "the cracks may be filled with dirt or debris": 1,
        "a series of parallel lines that intersect to form a grid": 1,
        "the lines may be of different thicknesses": 2,
        "the lines may be of different colors": 2,
        "the texture may be regular or irregular": 1,
        "the texture may be applied to a surface or object": 1,
        "a repeating pattern of shapes": 1,
        "sharp edges": 1,
        "a glossy or shiny surface": 2,
        "a transparent or translucent appearance": 1,
        "a three-dimensional structure": 1,
        "a series of small, round dots": 2,
        "evenly spaced": 4,
        "can be of any color": 1,
        "may be on a background of any color": 1,
        "may be in a regular or irregular pattern": 1,
        "closeup view": 1,
        "many small, thin strands": 1,
        "light reflecting off of strands": 1,
        "strands of different colors": 1,
        "a textured surface": 1,
        "small, irregularly shaped pieces": 1,
        "a variety of colors": 2,
        "a rough or bumpy surface": 3,
        "small, round spots": 1,
        "evenly distributed": 1,
        "same color as surrounding skin": 1,
        "darker than surrounding skin": 1,
        "intricate, lacy patterns": 1,
        "delicate and often transparent": 1,
        "light and airy": 1,
        "can be made of various materials, including paper, fabric, or metal": 1,
        "a thin, translucent fabric": 1,
        "a light, airy feel": 1,
        "a delicate or lacy appearance": 1,
        "straight lines forming a consistent grid": 1,
        "evenly spaced lines and intersections": 1,
        "a consistent color or tone throughout": 1,
        "a series of parallel lines": 2,
        "a repeating pattern": 1,
        "a raised or indented surface": 1,
        "a repeating pattern of hexagonal shapes": 1,
        "a honey-like color": 1,
        "a smooth, glossy surface": 1,
        "a repeating pattern of light and dark lines": 1,
        "the lines are usually perpendicular to each other": 1,
        "small, interconnected loops": 1,
        "intricate, detailed pattern": 1,
        "often made of lace or other delicate material": 1,
        "can be white, cream, or other light colors": 1,
        "often used for decoration": 1,
        "green leaves": 1,
        "stem": 1,
        "roots": 1,
        "flowers (optional)": 1,
        "fruit (optional)": 1,
        "can be straight or curved": 1,
        "may be of different colors": 3,
        "may be of different widths": 2,
        "may be of different thicknesses": 1,
        "a swirl or whorl pattern": 1,
        "two or more colors": 1,
        "a smooth or textured surface": 1,
        "a surface with a raised or relief pattern": 1,
        "a surface that is not smooth": 1,
        "a surface with a lot of texture": 1,
        "a surface that is not glossy or shiny": 1,
        "a repeating pattern of interlocking shapes": 1,
        "a regular, geometric shape": 1,
        "a consistent size and spacing between shapes": 1,
        "a symmetrical or nearly symmetrical design": 1,
        "straight or curved lines": 1,
        "a solid color or a limited color palette": 1,
        "a repeating pattern of curved shapes": 1,
        "usually brightly colored": 1,
        "often with a floral or geometric design": 1,
        "a series of small, evenly spaced holes": 1,
        "a surface with a regular pattern of indentations": 1,
        "a material with a porous or spongy appearance": 1,
        "a surface with small, shallow depressions": 1,
        "a matte or dull finish": 1,
        "a series of parallel, evenly spaced folds or creases": 1,
        "fabric that is gathered or puffed up in between the folds": 1,
        "a smooth, flat surface on either side of the folds": 1,
        "usually on a light background": 1,
        "can be any color": 1,
        "may be on a variety of surfaces": 1,
        "small, irregular holes or pores": 1,
        "a rough or spongy surface": 1,
        "light and dark areas where the pores are more or less dense": 1,
        "a road or street with many small holes": 1,
        "the surface is bumpy and uneven": 1,
        "the holes are usually circular or oval-shaped": 1,
        "the holes may be filled with water or debris": 1,
        "the surrounding area may be cracked or damaged": 1,
        "a series of overlapping plates or scales": 1,
        "a dry, rough, or bumpy surface": 1,
        "a dull or matte finish": 1,
        "a lack of luster or shine": 1,
        "blurred or out of focus": 1,
        "colors running together": 1,
        "a smeared or streaked appearance": 1,
        "a repeating pattern of interlocking curves": 1,
        "a raised or embossed surface": 1,
        "a glossy or matte finish": 1,
        "small, uniform dots": 1,
        "same size and shape": 1,
        "can be a variety of colors": 1,
        "may be shimmery or iridescent": 1,
        "a discolored area": 1,
        "a raised or bumpy surface": 1,
        "a change in color or opacity": 1,
        "a change in texture": 1,
        "a series of layers": 1,
        "each layer is of a different material": 1,
        "the layers are parallel to each other": 1,
        "the layers may be of different thicknesses": 1,
        "the layers may be of different colors": 1,
        "the layers may have different textures": 1,
        "alternating light and dark bands": 1,
        "regular, repeating pattern": 1,
        "can be horizontal, vertical, or diagonal": 1,
        "a series of raised bumps or ridges": 1,
        "may be arranged in a pattern": 1,
        "may be of different sizes": 1,
        "a spiral or whorl pattern": 1,
        "a light or dark color": 1,
        "a repeating pattern of lines or shapes": 1,
        "a contrast between light and dark areas": 1,
        "a series of raised, parallel lines": 1,
        "a honeycomb or grid-like appearance": 1,
        "a three-dimensional texture": 1,
        "a series of parallel, criss-crossing lines": 1,
        "a fabric or material with a textile weave": 1,
        "a surface with raised bumps or ridges": 1,
        "a surface with indentations or valleys": 1,
        "a surface with a complex, irregular pattern": 1,
        "a surface that appears dry or dehydrated": 1,
        "a repeating pattern of sharp angles": 1,
        "usually black and white": 1,
        "can be created with lines, shapes, or colors": 1,
        "often used to create a sense of movement or energy": 1
    },
    "freq_contains": {
        "a repeating pattern of light and dark bands": 1,
        "the bands are of different widths": 1,
        "the bands may be of different colors": 1,
        "the bands may be curved or straight": 1,
        "the bands may be parallel or intersecting": 1,
        "an uneven or mottled surface": 1,
        "a variety of colors or shades": 1,
        "a raised or bumpy texture": 1,
        "a matte finish": 1,
        "three or more strands of material woven together": 1,
        "a tight, interlocking pattern": 2,
        "small, round, and raised bumps": 1,
        "a smooth or glossy surface": 2,
        "a three-dimensional appearance": 4,
        "a light-reflecting quality": 1,
        "an uneven surface": 1,
        "raised or indented areas": 1,
        "a rough or bumpy feel": 1,
        "a repeating pattern of squares or rectangles": 2,
        "alternating light and dark colors": 1,
        "sharp, defined lines between the squares or rectangles": 1,
        "a web-like pattern": 1,
        "made of thin, silky strands": 1,
        "often found in dark, damp places": 1,
        "can be sticky to the touch": 1,
        "can be difficult to remove once entangled": 1,
        "a surface with cracks": 1,
        "the cracks may be straight or curved": 1,
        "the cracks may be of different sizes": 1,
        "the cracks may be close together or far apart": 1,
        "the cracks may be deep or shallow": 1,
        "the cracks may be filled with dirt or debris": 1,
        "a series of parallel lines that intersect to form a grid": 1,
        "the lines may be of different thicknesses": 2,
        "the lines may be of different colors": 2,
        "the texture may be regular or irregular": 1,
        "the texture may be applied to a surface or object": 1,
        "a repeating pattern of shapes": 1,
        "sharp edges": 1,
        "a glossy or shiny surface": 2,
        "a transparent or translucent appearance": 1,
        "a three-dimensional structure": 1,
        "a series of small, round dots": 2,
        "evenly spaced": 7,
        "can be of any color": 1,
        "may be on a background of any color": 1,
        "may be in a regular or irregular pattern": 1,
        "closeup view": 1,
        "many small, thin strands": 1,
        "light reflecting off of strands": 1,
        "strands of different colors": 1,
        "a textured surface": 1,
        "small, irregularly shaped pieces": 1,
        "a variety of colors": 4,
        "a rough or bumpy surface": 3,
        "small, round spots": 1,
        "evenly distributed": 1,
        "same color as surrounding skin": 1,
        "darker than surrounding skin": 1,
        "intricate, lacy patterns": 1,
        "delicate and often transparent": 1,
        "light and airy": 1,
        "can be made of various materials, including paper, fabric, or metal": 1,
        "a thin, translucent fabric": 1,
        "a light, airy feel": 1,
        "a delicate or lacy appearance": 1,
        "straight lines forming a consistent grid": 1,
        "evenly spaced lines and intersections": 1,
        "a consistent color or tone throughout": 1,
        "a series of parallel lines": 3,
        "a repeating pattern": 12,
        "a raised or indented surface": 1,
        "a repeating pattern of hexagonal shapes": 1,
        "a honey-like color": 1,
        "a smooth, glossy surface": 1,
        "a repeating pattern of light and dark lines": 1,
        "the lines are usually perpendicular to each other": 1,
        "small, interconnected loops": 1,
        "intricate, detailed pattern": 1,
        "often made of lace or other delicate material": 1,
        "can be white, cream, or other light colors": 1,
        "often used for decoration": 1,
        "green leaves": 1,
        "stem": 1,
        "roots": 1,
        "flowers (optional)": 1,
        "fruit (optional)": 1,
        "can be straight or curved": 1,
        "may be of different colors": 7,
        "may be of different widths": 2,
        "may be of different thicknesses": 4,
        "a swirl or whorl pattern": 1,
        "two or more colors": 1,
        "a smooth or textured surface": 1,
        "a surface with a raised or relief pattern": 1,
        "a surface that is not smooth": 1,
        "a surface with a lot of texture": 1,
        "a surface that is not glossy or shiny": 1,
        "a repeating pattern of interlocking shapes": 1,
        "a regular, geometric shape": 1,
        "a consistent size and spacing between shapes": 1,
        "a symmetrical or nearly symmetrical design": 1,
        "straight or curved lines": 1,
        "a solid color or a limited color palette": 1,
        "a repeating pattern of curved shapes": 1,
        "usually brightly colored": 1,
        "often with a floral or geometric design": 1,
        "a series of small, evenly spaced holes": 1,
        "a surface with a regular pattern of indentations": 1,
        "a material with a porous or spongy appearance": 1,
        "a surface with small, shallow depressions": 1,
        "a matte or dull finish": 1,
        "a series of parallel, evenly spaced folds or creases": 1,
        "fabric that is gathered or puffed up in between the folds": 1,
        "a smooth, flat surface on either side of the folds": 1,
        "usually on a light background": 1,
        "can be any color": 1,
        "may be on a variety of surfaces": 1,
        "small, irregular holes or pores": 1,
        "a rough or spongy surface": 1,
        "light and dark areas where the pores are more or less dense": 1,
        "a road or street with many small holes": 1,
        "the surface is bumpy and uneven": 1,
        "the holes are usually circular or oval-shaped": 1,
        "the holes may be filled with water or debris": 1,
        "the surrounding area may be cracked or damaged": 1,
        "a series of overlapping plates or scales": 1,
        "a dry, rough, or bumpy surface": 1,
        "a dull or matte finish": 1,
        "a lack of luster or shine": 1,
        "blurred or out of focus": 1,
        "colors running together": 1,
        "a smeared or streaked appearance": 1,
        "a repeating pattern of interlocking curves": 1,
        "a raised or embossed surface": 1,
        "a glossy or matte finish": 1,
        "small, uniform dots": 1,
        "same size and shape": 1,
        "can be a variety of colors": 1,
        "may be shimmery or iridescent": 1,
        "a discolored area": 1,
        "a raised or bumpy surface": 1,
        "a change in color or opacity": 1,
        "a change in texture": 1,
        "a series of layers": 1,
        "each layer is of a different material": 1,
        "the layers are parallel to each other": 1,
        "the layers may be of different thicknesses": 1,
        "the layers may be of different colors": 1,
        "the layers may have different textures": 1,
        "alternating light and dark bands": 1,
        "regular, repeating pattern": 1,
        "can be horizontal, vertical, or diagonal": 1,
        "a series of raised bumps or ridges": 1,
        "may be arranged in a pattern": 1,
        "may be of different sizes": 2,
        "a spiral or whorl pattern": 1,
        "a light or dark color": 1,
        "a repeating pattern of lines or shapes": 1,
        "a contrast between light and dark areas": 1,
        "a series of raised, parallel lines": 1,
        "a honeycomb or grid-like appearance": 1,
        "a three-dimensional texture": 1,
        "a series of parallel, criss-crossing lines": 1,
        "a fabric or material with a textile weave": 1,
        "a surface with raised bumps or ridges": 1,
        "a surface with indentations or valleys": 1,
        "a surface with a complex, irregular pattern": 1,
        "a surface that appears dry or dehydrated": 1,
        "a repeating pattern of sharp angles": 1,
        "usually black and white": 1,
        "can be created with lines, shapes, or colors": 1,
        "often used to create a sense of movement or energy": 1
    }
}